sibylengine/GFSDK_Aftermath_Lib.x64.dll
sibylengine/__init__.py
sibylengine/__init__.pyi
sibylengine/common.py
sibylengine/libdeflate.so
sibylengine/pycore.cp38-win_amd64.pyd
sibylengine/pycore.cp39-win_amd64.pyd
sibylengine/pycore.cpython-39-x86_64-linux-gnu.so
sibylengine/slang.dll
sibylengine/__pycache__/__init__.cpython-38.pyc
sibylengine/__pycache__/common.cpython-38.pyc
sibylengine/assets/brdfs/cc_amber_citrine_rgb.bsdf
sibylengine/assets/brdfs/cc_ibiza_sunset_rgb.bsdf
sibylengine/assets/fonts/opensans/LICENSE.txt
sibylengine/assets/fonts/opensans/OpenSans-Bold.ttf
sibylengine/assets/fonts/opensans/OpenSans-BoldItalic.ttf
sibylengine/assets/fonts/opensans/OpenSans-ExtraBold.ttf
sibylengine/assets/fonts/opensans/OpenSans-ExtraBoldItalic.ttf
sibylengine/assets/fonts/opensans/OpenSans-Italic.ttf
sibylengine/assets/fonts/opensans/OpenSans-Light.ttf
sibylengine/assets/fonts/opensans/OpenSans-LightItalic.ttf
sibylengine/assets/fonts/opensans/OpenSans-Regular.ttf
sibylengine/assets/fonts/opensans/OpenSans-SemiBold.ttf
sibylengine/assets/fonts/opensans/OpenSans-SemiBoldItalic.ttf
sibylengine/assets/images/matcap.png
sibylengine/assets/images/uv_checker.png
sibylengine/assets/meshes/cube.obj
sibylengine/assets/meshes/internal_sphere.obj
sibylengine/assets/meshes/plane.obj
sibylengine/assets/meshes/rectangle.obj
sibylengine/assets/meshes/sphere.obj
sibylengine/layouts/default.ini
sibylengine/layouts/new-layout.ini
sibylengine/shaders/common/complex.slang
sibylengine/shaders/common/geometry.slang
sibylengine/shaders/common/hashing.slang
sibylengine/shaders/common/linear-algebra.slang
sibylengine/shaders/common/mapping.slang
sibylengine/shaders/common/math.slang
sibylengine/shaders/common/microfacet.slang
sibylengine/shaders/common/octahedral.slang
sibylengine/shaders/common/override.slang
sibylengine/shaders/common/random.slang
sibylengine/shaders/common/ray.slang
sibylengine/shaders/common/rotation.slang
sibylengine/shaders/common/sampling.slang
sibylengine-0.0.4.dist-info/METADATA
sibylengine-0.0.4.dist-info/WHEEL
sibylengine-0.0.4.dist-info/top_level.txt
sibylengine-0.0.4.dist-info/RECORD
