Metadata-Version: 2.4
Name: sibylengine
Version: 0.0.4
Summary: Custom Vulkan renderer
Dynamic: summary
